start/__init__.py
start/pyiseasy.py
Oversimplepy-0.0.1.dist-info/METADATA
Oversimplepy-0.0.1.dist-info/WHEEL
Oversimplepy-0.0.1.dist-info/top_level.txt
Oversimplepy-0.0.1.dist-info/RECORD
