Metadata-Version: 2.1
Name: Oversimplepy
Version: 0.0.1
Summary: A small example package
Home-page: UNKNOWN
Author: TheOvercompensator
Author-email: sashwathdc10z63@gmail.com
License: UNKNOWN
Platform: UNKNOWN
Classifier: Programming Language :: Python :: 3
Classifier: Operating System :: OS Independent
Requires-Python: >=3.6
